setup.py
yask123/__init__.py
yask123.egg-info/PKG-INFO
yask123.egg-info/SOURCES.txt
yask123.egg-info/dependency_links.txt
yask123.egg-info/not-zip-safe
yask123.egg-info/top_level.txt