Metadata-Version: 1.0
Name: yask123
Version: 1
Summary: jkl
Home-page: http://google.com
Author: yask
Author-email: yask123@gmail.com
License: MIT
Platform: UNKNOWN
